async_annoy/__init__.py
async_annoy/constants.py
async_annoy/indexer.py
async_annoy-0.3.0.dist-info/LICENSE
async_annoy-0.3.0.dist-info/METADATA
async_annoy-0.3.0.dist-info/WHEEL
async_annoy-0.3.0.dist-info/RECORD
