Metadata-Version: 2.1
Name: async-annoy
Version: 0.3.0
Summary: Asynchronous wrapper around the Annoy library for approximate nearest neighbor search.
Home-page: https://github.com/ryzhakar/async-annoy
License: MIT
Keywords: annoy,asynchronous,nearest neighbors,semantic search,vector database,search,aiorwlock
Author: Arthur Ryzhak
Author-email: ryzhakar@gmail.com
Requires-Python: >=3.10,<4.0
Classifier: Development Status :: 3 - Alpha
Classifier: Intended Audience :: Developers
Classifier: License :: OSI Approved :: MIT License
Classifier: Operating System :: OS Independent
Classifier: Programming Language :: Python :: 3
Classifier: Programming Language :: Python :: 3.10
Classifier: Programming Language :: Python :: 3.11
Classifier: Programming Language :: Python :: 3.12
Classifier: Topic :: Scientific/Engineering :: Artificial Intelligence
Classifier: Topic :: Software Development :: Libraries :: Python Modules
Requires-Dist: aiorwlock (>=1.4.0,<2.0.0)
Requires-Dist: annoy (>=1.17.3,<2.0.0)
Requires-Dist: numpy (>=1.26.4,<2.0.0)
Requires-Dist: python-dotenv (>=1.0.1,<2.0.0)
Project-URL: Repository, https://github.com/ryzhakar/async-annoy
